setup.cfg
setup.py
ukpcode/__init__.py
ukpcode/constants.py
ukpcode/exceptions.py
ukpcode/tests.py
ukpcode.egg-info/PKG-INFO
ukpcode.egg-info/SOURCES.txt
ukpcode.egg-info/dependency_links.txt
ukpcode.egg-info/top_level.txt