Metadata-Version: 1.1
Name: ukpcode
Version: 0.0.1a2
Summary: UK post code library
Home-page: https://github.com/andersonbispo/ukpcode
Author: Anderson Bispo
Author-email: anderson.bispo@gmail.com
License: MIT
Keywords: format validate uk post code
Platform: UNKNOWN
Classifier: Development Status :: 3 - Alpha
Classifier: Intended Audience :: Developers
Classifier: Topic :: Software Development :: Build Tools
Classifier: License :: OSI Approved :: MIT License
Classifier: Programming Language :: Python :: 2
Classifier: Programming Language :: Python :: 2.7
Classifier: Programming Language :: Python :: 3
Classifier: Programming Language :: Python :: 3.3
Classifier: Programming Language :: Python :: 3.4
Classifier: Programming Language :: Python :: 3.5
Classifier: Programming Language :: Python :: 3.6
